<?xml version="1.0" encoding="UTF-8" standalone="no"?>
<configuration version="1.0.10.0">
  <General>
    <HarmonyPath path="../microchip/harmony/v1_09"/>
    <Processor name=""/>
    <ForceOptimization flag="false"/>
    <MergeStrategy flag="USER_ALL"/>
  </General>
  <Manifest>
    <Files>
      <File>
        <Name>ISR_Support.h</Name>
        <Path>Header Files/FreeRTOS/portable/MPLAB/PIC32MX</Path>
      </File>
      <File>
        <Name>semphr.h</Name>
        <Path>Header Files/FreeRTOS</Path>
      </File>
      <File>
        <Name>drv_usbfs_local.h</Name>
        <Path>Header Files/framework/driver/usb/usbfs/src</Path>
      </File>
      <File>
        <Name>queue.h</Name>
        <Path>Header Files/FreeRTOS</Path>
      </File>
      <File>
        <Name>portmacro.h</Name>
        <Path>Header Files/FreeRTOS/portable/MPLAB/PIC32MX</Path>
      </File>
      <File>
        <Name>croutine.c</Name>
        <Path>Source Files/FreeRTOS</Path>
      </File>
      <File>
        <Name>drv_usbhs.h</Name>
        <Path>Header Files/framework/driver/usb/usbhs</Path>
      </File>
      <File>
        <Name>drv_usbfs_static.h</Name>
        <Path>Header Files/framework/driver/usb/usbfs</Path>
      </File>
      <File>
        <Name>port_asm.S</Name>
        <Path>Source Files/FreeRTOS/portable/MPLAB/PIC32MX</Path>
      </File>
      <File>
        <Name>usb_device_local.h</Name>
        <Path>Header Files/framework/usb/src</Path>
      </File>
      <File>
        <Name>mpu_prototypes.h</Name>
        <Path>Header Files/FreeRTOS</Path>
      </File>
      <File>
        <Name>usb_chapter_9.h</Name>
        <Path>Header Files/framework/usb</Path>
      </File>
      <File>
        <Name>list.h</Name>
        <Path>Header Files/FreeRTOS</Path>
      </File>
      <File>
        <Name>peripheral_common.h</Name>
        <Path>Header Files/framework/peripheral</Path>
      </File>
      <File>
        <Name>sys_int_pic32.c</Name>
        <Path>Source Files/framework/system/int/src</Path>
      </File>
      <File>
        <Name>usb_device.c</Name>
        <Path>Source Files/framework/usb/src/dynamic</Path>
      </File>
      <File>
        <Name>sys_clk.h</Name>
        <Path>Header Files/framework/system/clk</Path>
      </File>
      <File>
        <Name>port.c</Name>
        <Path>Source Files/FreeRTOS/portable/MPLAB/PIC32MX</Path>
      </File>
      <File>
        <Name>usb_device.h</Name>
        <Path>Header Files/framework/usb</Path>
      </File>
      <File>
        <Name>sys_int_private.h</Name>
        <Path>Header Files/framework/system/int/src</Path>
      </File>
      <File>
        <Name>deprecated_definitions.h</Name>
        <Path>Header Files/FreeRTOS</Path>
      </File>
      <File>
        <Name>system.h</Name>
        <Path>Header Files/framework/system</Path>
      </File>
      <File>
        <Name>usb_cdc.h</Name>
        <Path>Header Files/framework/usb</Path>
      </File>
      <File>
        <Name>drv_usbfs.h</Name>
        <Path>Header Files/framework/driver/usb/usbfs</Path>
      </File>
      <File>
        <Name>timers.h</Name>
        <Path>Header Files/FreeRTOS</Path>
      </File>
      <File>
        <Name>usb_device_cdc_local.h</Name>
        <Path>Header Files/framework/usb/src</Path>
      </File>
      <File>
        <Name>task.h</Name>
        <Path>Header Files/FreeRTOS</Path>
      </File>
      <File>
        <Name>sys_int.h</Name>
        <Path>Header Files/framework/system/int</Path>
      </File>
      <File>
        <Name>osal_freertos.h</Name>
        <Path>Header Files/framework/osal/src</Path>
      </File>
      <File>
        <Name>drv_usb.h</Name>
        <Path>Header Files/framework/driver/usb</Path>
      </File>
      <File>
        <Name>osal_impl_basic.h</Name>
        <Path>Header Files/framework/osal/src</Path>
      </File>
      <File>
        <Name>peripheral_common_32bit.h</Name>
        <Path>Header Files/framework/peripheral</Path>
      </File>
      <File>
        <Name>usb_billboard.h</Name>
        <Path>Header Files/framework/usb</Path>
      </File>
      <File>
        <Name>drv_usbfs.c</Name>
        <Path>Source Files/framework/driver/usb/usbfs/src/dynamic</Path>
      </File>
      <File>
        <Name>list.c</Name>
        <Path>Source Files/FreeRTOS</Path>
      </File>
      <File>
        <Name>sys_devcon.c</Name>
        <Path>Source Files/framework/system/devcon/src</Path>
      </File>
      <File>
        <Name>osal.h</Name>
        <Path>Header Files/framework/osal</Path>
      </File>
      <File>
        <Name>usb_device_cdc.h</Name>
        <Path>Header Files/framework/usb</Path>
      </File>
      <File>
        <Name>StackMacros.h</Name>
        <Path>Header Files/FreeRTOS</Path>
      </File>
      <File>
        <Name>osal_freertos.c</Name>
        <Path>Source Files/framework/osal/src</Path>
      </File>
      <File>
        <Name>tasks.c</Name>
        <Path>Source Files/FreeRTOS</Path>
      </File>
      <File>
        <Name>usb_common.h</Name>
        <Path>Header Files/framework/usb</Path>
      </File>
      <File>
        <Name>sys_ports.h</Name>
        <Path>Header Files/framework/system/ports</Path>
      </File>
      <File>
        <Name>projdefs.h</Name>
        <Path>Header Files/FreeRTOS</Path>
      </File>
      <File>
        <Name>portable.h</Name>
        <Path>Header Files/FreeRTOS</Path>
      </File>
      <File>
        <Name>croutine.h</Name>
        <Path>Header Files/FreeRTOS</Path>
      </File>
      <File>
        <Name>sys_common.h</Name>
        <Path>Header Files/framework/system/common</Path>
      </File>
      <File>
        <Name>sys_buffer.h</Name>
        <Path>Header Files/framework/system/common</Path>
      </File>
      <File>
        <Name>usb_device_mapping.h</Name>
        <Path>Header Files/framework/usb/src</Path>
      </File>
      <File>
        <Name>event_groups.h</Name>
        <Path>Header Files/FreeRTOS</Path>
      </File>
      <File>
        <Name>osal_impl_none.h</Name>
        <Path>Header Files/framework/osal/src</Path>
      </File>
      <File>
        <Name>sys_clk_mapping.h</Name>
        <Path>Header Files/framework/system/clk</Path>
      </File>
      <File>
        <Name>osal_definitions.h</Name>
        <Path>Header Files/framework/osal</Path>
      </File>
      <File>
        <Name>sys_int_mapping.h</Name>
        <Path>Header Files/framework/system/int</Path>
      </File>
      <File>
        <Name>FreeRTOS.h</Name>
        <Path>Header Files/FreeRTOS</Path>
      </File>
      <File>
        <Name>gfx_palette.h</Name>
        <Path>Header Files/framework/gfx</Path>
      </File>
      <File>
        <Name>sys_devcon.h</Name>
        <Path>Header Files/framework/system/devcon</Path>
      </File>
      <File>
        <Name>event_groups.c</Name>
        <Path>Source Files/FreeRTOS</Path>
      </File>
      <File>
        <Name>drv_usbfs_device.c</Name>
        <Path>Source Files/framework/driver/usb/usbfs/src/dynamic</Path>
      </File>
      <File>
        <Name>sys_debug.h</Name>
        <Path>Header Files/framework/system/debug</Path>
      </File>
      <File>
        <Name>usb_device_cdc_acm.c</Name>
        <Path>Source Files/framework/usb/src/dynamic</Path>
      </File>
      <File>
        <Name>sys_module.h</Name>
        <Path>Header Files/framework/system/common</Path>
      </File>
      <File>
        <Name>sys_devcon_pic32mx.c</Name>
        <Path>Source Files/framework/system/devcon/src</Path>
      </File>
      <File>
        <Name>sys_devcon_local.h</Name>
        <Path>Header Files/framework/system/devcon/src</Path>
      </File>
      <File>
        <Name>drv_usbfs_variant_mapping.h</Name>
        <Path>Header Files/framework/driver/usb/usbfs/src</Path>
      </File>
      <File>
        <Name>timers.c</Name>
        <Path>Source Files/FreeRTOS</Path>
      </File>
      <File>
        <Name>mpu_wrappers.h</Name>
        <Path>Header Files/FreeRTOS</Path>
      </File>
      <File>
        <Name>peripheral.h</Name>
        <Path>Header Files/framework/peripheral</Path>
      </File>
      <File>
        <Name>heap_4.c</Name>
        <Path>Source Files/FreeRTOS/portable/MemMang</Path>
      </File>
      <File>
        <Name>sys_queue.h</Name>
        <Path>Header Files/framework/system/common</Path>
      </File>
      <File>
        <Name>usb_device_cdc.c</Name>
        <Path>Source Files/framework/usb/src/dynamic</Path>
      </File>
      <File>
        <Name>queue.c</Name>
        <Path>Source Files/FreeRTOS</Path>
      </File>
      <File>
        <Name>drv_usbfs_mapping.h</Name>
        <Path>Header Files/framework/driver/usb/usbfs</Path>
      </File>
    </Files>
    <Templates>
      <Template>
        <Name>system_config.h</Name>
        <Path>Header Files/app/system_config/pic32mx_usb_badge_int_dyn</Path>
        <Checksum>20AF1F40D4C18534809F9DAD99277622</Checksum>
      </Template>
      <Template>
        <Name>sys_clk_static.c</Name>
        <Path>Source Files/app/system_config/pic32mx_usb_badge_int_dyn/framework/system/clk/src</Path>
        <Checksum>6AF033A7E8ECB69981D88ED27526EF17</Checksum>
      </Template>
      <Template>
        <Name>main.c</Name>
        <Path>Source Files/app</Path>
      </Template>
      <Template>
        <Name>system_interrupt_a.S</Name>
        <Path>Source Files/app/system_config/pic32mx_usb_badge_int_dyn</Path>
        <Checksum>D920562575B92A0EBF9263BE8E58DFE6</Checksum>
      </Template>
      <Template>
        <Name>app.c</Name>
        <Path>Source Files/app</Path>
      </Template>
      <Template>
        <Name>system_definitions.h</Name>
        <Path>Header Files/app/system_config/pic32mx_usb_badge_int_dyn</Path>
        <Checksum>F96FFCCA8C7EA3EF6162F11C699FB8CC</Checksum>
      </Template>
      <Template>
        <Name>sys_clk_static.h</Name>
        <Path>Header Files/app/system_config/pic32mx_usb_badge_int_dyn/framework/system/clk</Path>
        <Checksum>B4BD59D8D7C4DA95DC5E3B57755FD352</Checksum>
      </Template>
      <Template>
        <Name>system_tasks.c</Name>
        <Path>Source Files/app/system_config/pic32mx_usb_badge_int_dyn</Path>
        <Checksum>BBACF1B8842E6DFF35D343F591F08EE4</Checksum>
      </Template>
      <Template>
        <Name>FreeRTOSConfig.h</Name>
        <Path>Header Files/app/system_config/pic32mx_usb_badge_int_dyn</Path>
        <Checksum>A25EEB5A50C3AA73BDF82AC4A61E34E4</Checksum>
      </Template>
      <Template>
        <Name>system_init.c</Name>
        <Path>Source Files/app/system_config/pic32mx_usb_badge_int_dyn</Path>
        <Checksum>67FDD6FDB84210E5A4A18ED5C745D6AD</Checksum>
      </Template>
      <Template>
        <Name>sys_ports_static.c</Name>
        <Path>Source Files/app/system_config/pic32mx_usb_badge_int_dyn/framework/system/ports/src</Path>
        <Checksum>7F062AB47AFAC69E501D1EF58EEB5E0E</Checksum>
      </Template>
      <Template>
        <Name>system_exceptions.c</Name>
        <Path>Source Files/app/system_config/pic32mx_usb_badge_int_dyn</Path>
        <Checksum>C111969CA43D6CEA1E9E33A6164E7AE0</Checksum>
      </Template>
      <Template>
        <Name>app.h</Name>
        <Path>Header Files/app</Path>
      </Template>
      <Template>
        <Name>system_interrupt.c</Name>
        <Path>Source Files/app/system_config/pic32mx_usb_badge_int_dyn</Path>
        <Checksum>1C2BCB9D8C0FE4A230C8BE67D8817639</Checksum>
      </Template>
      <Template>
        <Name>rtos_hooks.c</Name>
        <Path>Source Files/app/system_config/pic32mx_usb_badge_int_dyn</Path>
        <Checksum>FA52743264536E5207D2ADBE57B48D05</Checksum>
      </Template>
    </Templates>
    <CompilerItems>
      <C32-AS>
        <Include value="../../../microchip/harmony/v1_09/third_party/rtos/FreeRTOS/Source/portable/MPLAB/PIC32MX"/>
        <Include value="../../../microchip/harmony/v1_09/third_party/rtos/FreeRTOS/Source/include"/>
        <Include value="../src/system_config/pic32mx_usb_badge_int_dyn"/>
      </C32-AS>
      <C32>
        <Include value="/home/paul/Harmony-Badge-2018/firmware/src"/>
        <Include value="/home/paul/Harmony-Badge-2018/firmware/src/system_config/pic32mx_usb_badge_int_dyn"/>
        <Include value="/home/paul/Harmony-Badge-2018/firmware/src/pic32mx_usb_badge_int_dyn"/>
        <Include value="/home/paul/microchip/harmony/v1_09/framework"/>
        <Include value="/home/paul/Harmony-Badge-2018/firmware/src/system_config/pic32mx_usb_badge_int_dyn/framework"/>
        <Include value="../../../microchip/harmony/v1_09/third_party/rtos/FreeRTOS/Source/portable/MPLAB/PIC32MX"/>
        <Include value="../../../microchip/harmony/v1_09/third_party/rtos/FreeRTOS/Source/include"/>
        <Include value="../src/system_config/pic32mx_usb_badge_int_dyn"/>
        <Define value="__XC"/>
      </C32>
    </CompilerItems>
    <Libraries>
      <Library value="../../../microchip/harmony/v1_09/bin/framework/peripheral/PIC32MX270F256D_peripherals.a"/>
    </Libraries>
  </Manifest>
</configuration>
